spacecomx/cdk_billing_alarm/__init__.py
spacecomx/cdk_billing_alarm/py.typed
spacecomx/cdk_billing_alarm/_jsii/__init__.py
spacecomx/cdk_billing_alarm/_jsii/cdk-billing-alarm@1.0.20.jsii.tgz
spacecomx.cdk_billing_alarm-1.0.20.dist-info/LICENSE
spacecomx.cdk_billing_alarm-1.0.20.dist-info/METADATA
spacecomx.cdk_billing_alarm-1.0.20.dist-info/WHEEL
spacecomx.cdk_billing_alarm-1.0.20.dist-info/top_level.txt
spacecomx.cdk_billing_alarm-1.0.20.dist-info/RECORD
