Metadata-Version: 2.1
Name: spacecomx.cdk-billing-alarm
Version: 1.0.20
Summary: It sets up an estimated monthly billing alarm associated with an email address endpoint. It then subscribes that endpoint to an SNS Topic created by the package or it can use an existing SNS Topic Arn. The CDK construct can be used to implement multiple customizable billing alarms for single or master/payer account e.g (AWS Organization).
Home-page: https://github.com/spacecomx/cdk-billing-alarm.git
Author: Wayne Gibson<wayne.gibson@spacecomx.com>
License: MIT
Project-URL: Source, https://github.com/spacecomx/cdk-billing-alarm.git
Platform: UNKNOWN
Classifier: Intended Audience :: Developers
Classifier: Operating System :: OS Independent
Classifier: Programming Language :: JavaScript
Classifier: Programming Language :: Python :: 3 :: Only
Classifier: Programming Language :: Python :: 3.6
Classifier: Programming Language :: Python :: 3.7
Classifier: Programming Language :: Python :: 3.8
Classifier: Programming Language :: Python :: 3.9
Classifier: Typing :: Typed
Classifier: Development Status :: 5 - Production/Stable
Classifier: License :: OSI Approved
Requires-Python: >=3.6
License-File: LICENSE
Requires-Dist: aws-cdk.aws-cloudwatch-actions (<2.0.0,>=1.125.0)
Requires-Dist: aws-cdk.aws-cloudwatch (<2.0.0,>=1.125.0)
Requires-Dist: aws-cdk.aws-sns-subscriptions (<2.0.0,>=1.125.0)
Requires-Dist: aws-cdk.aws-sns (<2.0.0,>=1.125.0)
Requires-Dist: aws-cdk.core (<2.0.0,>=1.125.0)
Requires-Dist: constructs (<4.0.0,>=3.2.27)
Requires-Dist: jsii (<2.0.0,>=1.35.0)
Requires-Dist: publication (>=0.0.3)
